mmkg_visual_entity_recognition/__init__.py
mmkg_visual_entity_recognition/app.py
mmkg_visual_entity_recognition/classes.txt
mmkg_visual_entity_recognition/models.py
mmkg_visual_entity_recognition-0.2.6.dist-info/METADATA
mmkg_visual_entity_recognition-0.2.6.dist-info/WHEEL
mmkg_visual_entity_recognition-0.2.6.dist-info/top_level.txt
mmkg_visual_entity_recognition-0.2.6.dist-info/RECORD
