Metadata-Version: 2.1
Name: mmkg-visual-entity-recognition
Version: 0.2.6
Summary: MMKG Models
Home-page: https://github.com/vivym/mmkg-visual-entity-recognition
Download-URL: https://github.com/vivym/mmkg-visual-entity-recognition/tags
Author: Ming Yang
Author-email: ymviv@qq.com
Requires-Python: >=3.9
Requires-Dist: pillow
Requires-Dist: aiofiles
Requires-Dist: fastapi
Requires-Dist: uvicorn[standard]
Requires-Dist: python-multipart
